kserve_storage/__init__.py
kserve_storage/kserve_storage.py
kserve_storage/logging.py
kserve_storage-0.16.0rc1.dist-info/METADATA
kserve_storage-0.16.0rc1.dist-info/WHEEL
kserve_storage-0.16.0rc1.dist-info/top_level.txt
kserve_storage-0.16.0rc1.dist-info/RECORD
