Metadata-Version: 2.4
Name: kserve-storage
Version: 0.16.0rc1
Summary: KServe Storage Handler. This module is responsible to download the models from the provided source
Author-email: The KServe Authors <dsun20@bloomberg.net>, The KServe Authors <fspolti@redhat.com>
License: https://github.com/kserve/kserve/blob/master/LICENSE
Classifier: Intended Audience :: Developers
Classifier: Programming Language :: Python :: 3
Classifier: License :: OSI Approved :: Apache Software License
Classifier: Operating System :: OS Independent
Requires-Python: <3.13,>=3.9
Requires-Dist: requests<3.0.0,>=2.32.2
Requires-Dist: google-cloud-storage<3.0.0,>=2.14.0
Requires-Dist: azure-storage-blob<13.0.0,>=12.20.0
Requires-Dist: azure-storage-file-share<13.0.0,>=12.16.0
Requires-Dist: azure-identity<2.0.0,>=1.15.0
Requires-Dist: boto3<2.0.0,>=1.29.0
Requires-Dist: huggingface-hub[hf-transfer]>=0.32.0
